AUTHORS.rst
LICENSE
MANIFEST.in
README.rst
setup.py
django_redis_cache_qube.egg-info/PKG-INFO
django_redis_cache_qube.egg-info/SOURCES.txt
django_redis_cache_qube.egg-info/dependency_links.txt
django_redis_cache_qube.egg-info/requires.txt
django_redis_cache_qube.egg-info/top_level.txt
redis_cache/__init__.py
redis_cache/cache.py
redis_cache/compressors.py
redis_cache/connection.py
redis_cache/constants.py
redis_cache/serializers.py
redis_cache/sharder.py
redis_cache/utils.py
redis_cache/backends/__init__.py
redis_cache/backends/base.py
redis_cache/backends/dummy.py
redis_cache/backends/multiple.py
redis_cache/backends/single.py