Metadata-Version: 2.1
Name: django-redis-cache-qube
Version: 3.0.2
Summary: Redis Cache Backend for Django
Home-page: http://github.com/sebleier/django-redis-cache/
Author: Sean Bleier
Author-email: sebleier@gmail.com
License: BSD
Classifier: Programming Language :: Python
Classifier: Programming Language :: Python :: 3.6
Classifier: Programming Language :: Python :: 3.7
Classifier: Programming Language :: Python :: 3.8
Classifier: License :: OSI Approved :: BSD License
Classifier: Operating System :: OS Independent
Classifier: Topic :: Software Development :: Libraries
Classifier: Topic :: Utilities
Classifier: Environment :: Web Environment
Classifier: Framework :: Django
Classifier: Framework :: Django :: 3.0
Classifier: Framework :: Django :: 3.1
Classifier: Framework :: Django :: 3.2
License-File: LICENSE
License-File: AUTHORS.rst
